{"path":"/io/realm/mongodb/mongo/MongoDatabase","root":{"type":"root","children":[{"type":"heading","children":[{"type":"text","value":"io.realm.mongodb.mongo.MongoDatabase"}],"depth":1},{"type":"html","value":"<a name=\"io_realm_mongodb_mongo_MongoDatabase\" ></a>","anchorName":"io_realm_mongodb_mongo_MongoDatabase","entity":{"canonicalName":"io.realm.mongodb.mongo.MongoDatabase","pageUri":"/io/realm/mongodb/mongo/MongoDatabase","data":{"category":"class","containingPackage":"io.realm.mongodb.mongo","simpleTypeName":"MongoDatabase","classType":"class"},"type":"internal"}},{"type":"paragraph","children":[{"type":"emphasis","children":[{"type":"text","value":"Superclass:"}]}]},{"type":"list","children":[{"type":"listItem","children":[{"type":"link","children":[{"type":"text","value":"java.lang.Object"}],"targetCanonicalName":"java.lang.Object","isPending":false,"linkText":"java.lang.Object","url":"https://docs.oracle.com/javase/7/docs/api/java/lang/Object.html","title":"java.lang.Object","entityType":"external"}]}],"ordered":false},{"type":"root","children":[{"type":"paragraph","children":[{"type":"text","value":"The RemoteMongoDatabase provides access to its "},{"type":"strong","children":[{"type":"text","value":"Document"},{"type":"text","value":" (?)"}],"targetCanonicalName":"Document","isPending":true,"linkText":"Document"},{"type":"text","value":" "},{"type":"link","children":[{"type":"text","value":"MongoCollection"}],"targetCanonicalName":"io.realm.mongodb.mongo.MongoCollection","isPending":false,"linkText":"MongoCollection","url":"/io/realm/mongodb/mongo/MongoCollection#io_realm_mongodb_mongo_MongoCollection","title":"MongoCollection","entityType":"internal"},{"type":"text","value":"s."}]}],"position":{"start":{"line":1,"column":1,"offset":0},"end":{"line":1,"column":1878,"offset":1877}}},{"type":"heading","children":[{"type":"text","value":"Method Summary"}],"depth":2},{"type":"table","children":[{"type":"tableRow","children":[{"type":"tableCell","children":[{"type":"text","value":"Modifier and Type"}]},{"type":"tableCell","children":[{"type":"text","value":"Method and Description"}]}]},{"type":"tableRow","children":[{"type":"tableCell","children":[{"type":"text","value":"public"},{"type":"text","value":" "},{"type":"link","children":[{"type":"text","value":"String"}],"targetCanonicalName":"java.lang.String","isPending":false,"linkText":"String","url":"https://docs.oracle.com/javase/7/docs/api/java/lang/String.html","title":"String","entityType":"external"}]},{"type":"tableCell","children":[{"type":"paragraph","children":[{"type":"link","children":[{"type":"text","value":"getName"}],"targetCanonicalName":"io.realm.mongodb.mongo.MongoDatabase.getName()","isPending":false,"linkText":"getName","url":"/io/realm/mongodb/mongo/MongoDatabase#io_realm_mongodb_mongo_MongoDatabase_getName__","title":"getName","entityType":"internal"},{"type":"text","value":" "},{"type":"text","value":"("},{"type":"text","value":")"}]},{"type":"paragraph","children":[{"type":"root","children":[{"type":"text","value":"Gets the name of the database.","position":{"start":{"line":1,"column":1,"offset":0},"end":{"line":1,"column":31,"offset":30}}}],"position":{"start":{"line":1,"column":1,"offset":0},"end":{"line":1,"column":31,"offset":30}}}]}]}]},{"type":"tableRow","children":[{"type":"tableCell","children":[{"type":"text","value":"public"},{"type":"text","value":" "},{"type":"link","children":[{"type":"text","value":"MongoCollection"}],"targetCanonicalName":"io.realm.mongodb.mongo.MongoCollection","isPending":false,"linkText":"MongoCollection","url":"/io/realm/mongodb/mongo/MongoCollection#io_realm_mongodb_mongo_MongoCollection","title":"MongoCollection","entityType":"internal"}]},{"type":"tableCell","children":[{"type":"paragraph","children":[{"type":"link","children":[{"type":"text","value":"getCollection"}],"targetCanonicalName":"io.realm.mongodb.mongo.MongoDatabase.getCollection(String)","isPending":false,"linkText":"getCollection","url":"/io/realm/mongodb/mongo/MongoDatabase#io_realm_mongodb_mongo_MongoDatabase_getCollection_String_","title":"getCollection","entityType":"internal"},{"type":"text","value":" "},{"type":"text","value":"("},{"type":"link","children":[{"type":"text","value":"String"}],"targetCanonicalName":"java.lang.String","isPending":false,"linkText":"String","url":"https://docs.oracle.com/javase/7/docs/api/java/lang/String.html","title":"String","entityType":"external"},{"type":"text","value":" collectionName"},{"type":"text","value":")"}]},{"type":"paragraph","children":[{"type":"root","children":[{"type":"text","value":"Gets a collection.","position":{"start":{"line":1,"column":1,"offset":0},"end":{"line":1,"column":19,"offset":18}}}],"position":{"start":{"line":1,"column":1,"offset":0},"end":{"line":1,"column":19,"offset":18}}}]}]}]},{"type":"tableRow","children":[{"type":"tableCell","children":[{"type":"text","value":"public"},{"type":"text","value":" "},{"type":"link","children":[{"type":"text","value":"MongoCollection"}],"targetCanonicalName":"io.realm.mongodb.mongo.MongoCollection","isPending":false,"linkText":"MongoCollection","url":"/io/realm/mongodb/mongo/MongoCollection#io_realm_mongodb_mongo_MongoCollection","title":"MongoCollection","entityType":"internal"}]},{"type":"tableCell","children":[{"type":"paragraph","children":[{"type":"link","children":[{"type":"text","value":"getCollection"}],"targetCanonicalName":"io.realm.mongodb.mongo.MongoDatabase.getCollection(String, Class<DocumentT>)","isPending":false,"linkText":"getCollection","url":"/io/realm/mongodb/mongo/MongoDatabase#io_realm_mongodb_mongo_MongoDatabase_getCollection_String__Class_DocumentT__","title":"getCollection","entityType":"internal"},{"type":"text","value":" "},{"type":"text","value":"<"},{"type":"strong","children":[{"type":"text","value":"DocumentT"},{"type":"text","value":" (?)"}],"targetCanonicalName":"DocumentT","isPending":true,"linkText":"DocumentT"},{"type":"text","value":" "},{"type":"text","value":">"},{"type":"text","value":"("},{"type":"link","children":[{"type":"text","value":"String"}],"targetCanonicalName":"java.lang.String","isPending":false,"linkText":"String","url":"https://docs.oracle.com/javase/7/docs/api/java/lang/String.html","title":"String","entityType":"external"},{"type":"text","value":" collectionName, "},{"type":"link","children":[{"type":"text","value":"java.lang.Class<DocumentT>"}],"targetCanonicalName":"java.lang.Class","isPending":false,"linkText":"java.lang.Class<DocumentT>","url":"https://docs.oracle.com/javase/7/docs/api/java/lang/Class.html","title":"java.lang.Class<DocumentT>","entityType":"external"},{"type":"text","value":" documentClass"},{"type":"text","value":")"}]},{"type":"paragraph","children":[{"type":"root","children":[{"type":"text","value":"Gets a collection, with a specific default document class.","position":{"start":{"line":1,"column":1,"offset":0},"end":{"line":1,"column":59,"offset":58}}}],"position":{"start":{"line":1,"column":1,"offset":0},"end":{"line":1,"column":59,"offset":58}}}]}]}]}],"align":[null,null]},{"type":"heading","children":[{"type":"text","value":"Method Detail"}],"depth":2},{"type":"heading","children":[{"type":"text","value":"getName"}],"depth":3},{"type":"html","value":"<a name=\"io_realm_mongodb_mongo_MongoDatabase_getName__\" ></a>","anchorName":"io_realm_mongodb_mongo_MongoDatabase_getName__","entity":{"canonicalName":"io.realm.mongodb.mongo.MongoDatabase.getName()","pageUri":"/io/realm/mongodb/mongo/MongoDatabase","type":"internal"}},{"type":"heading","children":[{"type":"text","value":"public"},{"type":"text","value":" "},{"type":"link","children":[{"type":"text","value":"String"}],"targetCanonicalName":"java.lang.String","isPending":false,"linkText":"String","url":"https://docs.oracle.com/javase/7/docs/api/java/lang/String.html","title":"String","entityType":"external"},{"type":"text","value":" getName "},{"type":"text","value":"("},{"type":"text","value":")"}],"depth":4},{"type":"root","children":[{"type":"text","value":"Gets the name of the database.","position":{"start":{"line":1,"column":1,"offset":0},"end":{"line":1,"column":31,"offset":30}}}],"position":{"start":{"line":1,"column":1,"offset":0},"end":{"line":1,"column":31,"offset":30}}},{"type":"heading","children":[{"type":"text","value":"getCollection"}],"depth":3},{"type":"html","value":"<a name=\"io_realm_mongodb_mongo_MongoDatabase_getCollection_String_\" ></a>","anchorName":"io_realm_mongodb_mongo_MongoDatabase_getCollection_String_","entity":{"canonicalName":"io.realm.mongodb.mongo.MongoDatabase.getCollection(String)","pageUri":"/io/realm/mongodb/mongo/MongoDatabase","type":"internal"}},{"type":"heading","children":[{"type":"text","value":"public"},{"type":"text","value":" "},{"type":"link","children":[{"type":"text","value":"MongoCollection"}],"targetCanonicalName":"io.realm.mongodb.mongo.MongoCollection","isPending":false,"linkText":"MongoCollection","url":"/io/realm/mongodb/mongo/MongoCollection#io_realm_mongodb_mongo_MongoCollection","title":"MongoCollection","entityType":"internal"},{"type":"text","value":" getCollection "},{"type":"text","value":"("},{"type":"link","children":[{"type":"text","value":"String"}],"targetCanonicalName":"java.lang.String","isPending":false,"linkText":"String","url":"https://docs.oracle.com/javase/7/docs/api/java/lang/String.html","title":"String","entityType":"external"},{"type":"text","value":" collectionName"},{"type":"text","value":")"}],"depth":4},{"type":"root","children":[{"type":"text","value":"Gets a collection.","position":{"start":{"line":1,"column":1,"offset":0},"end":{"line":1,"column":19,"offset":18}}}],"position":{"start":{"line":1,"column":1,"offset":0},"end":{"line":1,"column":19,"offset":18}}},{"type":"heading","children":[{"type":"text","value":"Parameters"}],"depth":5},{"type":"list","children":[{"type":"listItem","children":[{"type":"inlineCode","value":"collectionName - "},{"type":"root","children":[{"type":"text","value":"the name of the collection to return","position":{"start":{"line":1,"column":1,"offset":0},"end":{"line":1,"column":37,"offset":36}}}],"position":{"start":{"line":1,"column":1,"offset":0},"end":{"line":1,"column":37,"offset":36}}}]}],"ordered":false},{"type":"html","value":"<a name=\"io_realm_mongodb_mongo_MongoDatabase_getCollection_String__Class_DocumentT__\" ></a>","anchorName":"io_realm_mongodb_mongo_MongoDatabase_getCollection_String__Class_DocumentT__","entity":{"canonicalName":"io.realm.mongodb.mongo.MongoDatabase.getCollection(String, Class<DocumentT>)","pageUri":"/io/realm/mongodb/mongo/MongoDatabase","type":"internal"}},{"type":"heading","children":[{"type":"text","value":"public"},{"type":"text","value":" "},{"type":"link","children":[{"type":"text","value":"MongoCollection"}],"targetCanonicalName":"io.realm.mongodb.mongo.MongoCollection","isPending":false,"linkText":"MongoCollection","url":"/io/realm/mongodb/mongo/MongoCollection#io_realm_mongodb_mongo_MongoCollection","title":"MongoCollection","entityType":"internal"},{"type":"text","value":" getCollection "},{"type":"text","value":"<"},{"type":"strong","children":[{"type":"text","value":"DocumentT"},{"type":"text","value":" (?)"}],"targetCanonicalName":"DocumentT","isPending":true,"linkText":"DocumentT"},{"type":"text","value":" "},{"type":"text","value":">"},{"type":"text","value":"("},{"type":"link","children":[{"type":"text","value":"String"}],"targetCanonicalName":"java.lang.String","isPending":false,"linkText":"String","url":"https://docs.oracle.com/javase/7/docs/api/java/lang/String.html","title":"String","entityType":"external"},{"type":"text","value":" collectionName, "},{"type":"link","children":[{"type":"text","value":"java.lang.Class<DocumentT>"}],"targetCanonicalName":"java.lang.Class","isPending":false,"linkText":"java.lang.Class<DocumentT>","url":"https://docs.oracle.com/javase/7/docs/api/java/lang/Class.html","title":"java.lang.Class<DocumentT>","entityType":"external"},{"type":"text","value":" documentClass"},{"type":"text","value":")"}],"depth":4},{"type":"root","children":[{"type":"text","value":"Gets a collection, with a specific default document class.","position":{"start":{"line":1,"column":1,"offset":0},"end":{"line":1,"column":59,"offset":58}}}],"position":{"start":{"line":1,"column":1,"offset":0},"end":{"line":1,"column":59,"offset":58}}},{"type":"heading","children":[{"type":"text","value":"Type Parameters"}],"depth":5},{"type":"list","children":[{"type":"listItem","children":[{"type":"inlineCode","value":"DocumentT - "},{"type":"root","children":[{"type":"paragraph","children":[{"type":"text","value":"the type of the class to use instead of "},{"type":"inlineCode","value":"Document"},{"type":"text","value":"."}]}],"position":{"start":{"line":1,"column":1,"offset":0},"end":{"line":1,"column":246,"offset":245}}}]}],"ordered":false},{"type":"heading","children":[{"type":"text","value":"Parameters"}],"depth":5},{"type":"list","children":[{"type":"listItem","children":[{"type":"inlineCode","value":"collectionName - "},{"type":"root","children":[{"type":"text","value":"the name of the collection to return","position":{"start":{"line":1,"column":1,"offset":0},"end":{"line":1,"column":37,"offset":36}}}],"position":{"start":{"line":1,"column":1,"offset":0},"end":{"line":1,"column":37,"offset":36}}}]},{"type":"listItem","children":[{"type":"inlineCode","value":"documentClass - "},{"type":"root","children":[{"type":"text","value":"the default class to cast any documents returned from the database into.","position":{"start":{"line":1,"column":1,"offset":0},"end":{"line":1,"column":73,"offset":72}}}],"position":{"start":{"line":1,"column":1,"offset":0},"end":{"line":1,"column":73,"offset":72}}}]}],"ordered":false}]}}