{"path":"/io/realm/RealmChangeListener","root":{"type":"root","children":[{"type":"heading","children":[{"type":"text","value":"io.realm.RealmChangeListener<T>"}],"depth":1},{"type":"html","value":"<a name=\"io_realm_RealmChangeListener\" ></a>","anchorName":"io_realm_RealmChangeListener","entity":{"canonicalName":"io.realm.RealmChangeListener","pageUri":"/io/realm/RealmChangeListener","data":{"category":"class","containingPackage":"io.realm","simpleTypeName":"RealmChangeListener","classType":"class"},"isExternal":false}},{"type":"root","children":[{"type":"paragraph","children":[{"type":"text","value":"RealmChangeListener can be registered with a "},{"type":"link","children":[{"type":"text","value":"Realm"}],"targetCanonicalName":"io.realm.Realm","isPending":false,"linkText":"Realm","url":"/io/realm/Realm#io_realm_Realm","title":"Realm","isExternal":false},{"type":"text","value":", "},{"type":"link","children":[{"type":"text","value":"RealmResults"}],"targetCanonicalName":"io.realm.RealmResults","isPending":false,"linkText":"RealmResults","url":"/io/realm/RealmResults#io_realm_RealmResults","title":"RealmResults","isExternal":false},{"type":"text","value":"or "},{"type":"link","children":[{"type":"text","value":"RealmObject"}],"targetCanonicalName":"io.realm.RealmObject","isPending":false,"linkText":"RealmObject","url":"/io/realm/RealmObject#io_realm_RealmObject","title":"RealmObject","isExternal":false},{"type":"text","value":"to receive a notification about updates."}]},{"type":"paragraph","children":[{"type":"paragraph","children":[{"type":"text","value":"When registered against a "},{"type":"inlineCode","value":"Realm"},{"type":"text","value":"you'll get notified when a Realm instance has been updated. Register against a "},{"type":"inlineCode","value":"RealmResults"},{"type":"text","value":", "},{"type":"inlineCode","value":"RealmList"},{"type":"text","value":", "},{"type":"inlineCode","value":"RealmDictionary"},{"type":"text","value":"or "},{"type":"inlineCode","value":"RealmObject"},{"type":"text","value":"to only get notified about changes to them."}]}],"position":{"start":{"line":3,"column":2,"offset":3382},"end":{"line":7,"column":2,"offset":6320}}},{"type":"paragraph","children":[{"type":"paragraph","children":[{"type":"text","value":"Realm instances on a thread without an "},{"type":"strong","children":[{"type":"text","value":"android.os.Looper"},{"type":"text","value":" (?)"}],"targetCanonicalName":"android.os.Looper","isPending":true,"linkText":"android.os.Looper"},{"type":"text","value":"cannot register a RealmChangeListener."}]}],"position":{"start":{"line":7,"column":2,"offset":6320},"end":{"line":9,"column":2,"offset":7513}}},{"type":"paragraph","children":[{"type":"paragraph","children":[{"type":"text","value":"All "},{"type":"link","children":[{"type":"text","value":"io.realm.RealmObject"}],"targetCanonicalName":"io.realm.RealmObject","isPending":false,"linkText":"io.realm.RealmObject","url":"/io/realm/RealmObject#io_realm_RealmObject","title":"io.realm.RealmObject","isExternal":false},{"type":"text","value":"and "},{"type":"link","children":[{"type":"text","value":"io.realm.RealmResults"}],"targetCanonicalName":"io.realm.RealmResults","isPending":false,"linkText":"io.realm.RealmResults","url":"/io/realm/RealmResults#io_realm_RealmResults","title":"io.realm.RealmResults","isExternal":false},{"type":"text","value":"will automatically contain their new values when the "},{"type":"strong","children":[{"type":"text","value":"#onChange(Object)"},{"type":"text","value":" (?)"}],"targetCanonicalName":"io.realm.RealmChangeListener.onChange(Object)","isPending":true,"linkText":"#onChange(Object)"},{"type":"text","value":"method is called. Normally this means that it isn't necessary to query again for those objects, but just invalidate any UI elements that are using them. If there is a chance that a object has been been deleted, it can be verified by using "},{"type":"strong","children":[{"type":"text","value":"RealmObject#isValid()"},{"type":"text","value":" (?)"}],"targetCanonicalName":"io.realm.RealmObject.isValid()","isPending":true,"linkText":"RealmObject#isValid()"},{"type":"text","value":"."}]}],"position":{"start":{"line":9,"column":2,"offset":7513},"end":{"line":13,"column":1237,"offset":12550}}}],"position":{"start":{"line":1,"column":1,"offset":0},"end":{"line":13,"column":1237,"offset":12550}}},{"type":"heading","children":[{"type":"text","value":"Method Summary"}],"depth":2},{"type":"table","children":[{"type":"tableRow","children":[{"type":"tableCell","children":[{"type":"text","value":"Modifier and Type"}]},{"type":"tableCell","children":[{"type":"text","value":"Method and Description"}]}]},{"type":"tableRow","children":[{"type":"tableCell","children":[{"type":"text","value":"public"},{"type":"text","value":" "},{"type":"strong","children":[{"type":"text","value":"void"},{"type":"text","value":" (?)"}],"targetCanonicalName":"void","isPending":true,"linkText":"void"}]},{"type":"tableCell","children":[{"type":"paragraph","children":[{"type":"link","children":[{"type":"text","value":"onChange"}],"targetCanonicalName":"io.realm.RealmChangeListener.onChange((T))","isPending":false,"linkText":"onChange","url":"/io/realm/RealmChangeListener#io_realm_RealmChangeListener_onChange__T__","title":"onChange","isExternal":false},{"type":"text","value":" "},{"type":"text","value":"("},{"type":"strong","children":[{"type":"text","value":"T"},{"type":"text","value":" (?)"}],"targetCanonicalName":"T","isPending":true,"linkText":"T"},{"type":"text","value":" t"},{"type":"text","value":")"}]},{"type":"paragraph","children":[{"type":"root","children":[{"type":"text","value":"Called when a transaction is committed.","position":{"start":{"line":1,"column":1,"offset":0},"end":{"line":1,"column":40,"offset":39}}}],"position":{"start":{"line":1,"column":1,"offset":0},"end":{"line":1,"column":40,"offset":39}}}]}]}]}],"align":[null,null]},{"type":"heading","children":[{"type":"text","value":"Method Detail"}],"depth":2},{"type":"heading","children":[{"type":"text","value":"onChange"}],"depth":3},{"type":"html","value":"<a name=\"io_realm_RealmChangeListener_onChange__T__\" ></a>","anchorName":"io_realm_RealmChangeListener_onChange__T__","entity":{"canonicalName":"io.realm.RealmChangeListener.onChange((T))","pageUri":"/io/realm/RealmChangeListener","isExternal":false}},{"type":"heading","children":[{"type":"text","value":"public"},{"type":"text","value":" "},{"type":"strong","children":[{"type":"text","value":"void"},{"type":"text","value":" (?)"}],"targetCanonicalName":"void","isPending":true,"linkText":"void"},{"type":"text","value":" onChange "},{"type":"text","value":"("},{"type":"strong","children":[{"type":"text","value":"T"},{"type":"text","value":" (?)"}],"targetCanonicalName":"T","isPending":true,"linkText":"T"},{"type":"text","value":" t"},{"type":"text","value":")"}],"depth":4},{"type":"root","children":[{"type":"text","value":"Called when a transaction is committed.","position":{"start":{"line":1,"column":1,"offset":0},"end":{"line":1,"column":40,"offset":39}}}],"position":{"start":{"line":1,"column":1,"offset":0},"end":{"line":1,"column":40,"offset":39}}}]}}